auto_ricer/__init__.py
auto_ricer/autoricer.py
auto_ricer-0.1.3.post1.dist-info/entry_points.txt
auto_ricer-0.1.3.post1.dist-info/LICENSE
auto_ricer-0.1.3.post1.dist-info/WHEEL
auto_ricer-0.1.3.post1.dist-info/METADATA
auto_ricer-0.1.3.post1.dist-info/RECORD
